LICENCE.txt
MANIFEST.in
README.rst
pyproject.toml
setup.cfg
setup.py
cmsplugin_blocks/__init__.py
cmsplugin_blocks/apps.py
cmsplugin_blocks/choices_helpers.py
cmsplugin_blocks/cms_plugins.py
cmsplugin_blocks/defaults.py
cmsplugin_blocks/exceptions.py
cmsplugin_blocks/managers.py
cmsplugin_blocks/modelfields.py
cmsplugin_blocks.egg-info/PKG-INFO
cmsplugin_blocks.egg-info/SOURCES.txt
cmsplugin_blocks.egg-info/dependency_links.txt
cmsplugin_blocks.egg-info/requires.txt
cmsplugin_blocks.egg-info/top_level.txt
cmsplugin_blocks.egg-info/zip-safe
cmsplugin_blocks/admin/__init__.py
cmsplugin_blocks/admin/accordion.py
cmsplugin_blocks/admin/album.py
cmsplugin_blocks/admin/feature.py
cmsplugin_blocks/admin/slider.py
cmsplugin_blocks/compat/__init__.py
cmsplugin_blocks/compat/cms.py
cmsplugin_blocks/compat/default_storage.py
cmsplugin_blocks/compat/editor_widget.py
cmsplugin_blocks/contrib/__init__.py
cmsplugin_blocks/contrib/disk.py
cmsplugin_blocks/contrib/django_configuration.py
cmsplugin_blocks/factories/__init__.py
cmsplugin_blocks/factories/accordion.py
cmsplugin_blocks/factories/album.py
cmsplugin_blocks/factories/card.py
cmsplugin_blocks/factories/container.py
cmsplugin_blocks/factories/feature.py
cmsplugin_blocks/factories/hero.py
cmsplugin_blocks/factories/slider.py
cmsplugin_blocks/factories/user.py
cmsplugin_blocks/forms/__init__.py
cmsplugin_blocks/forms/accordion.py
cmsplugin_blocks/forms/album.py
cmsplugin_blocks/forms/card.py
cmsplugin_blocks/forms/container.py
cmsplugin_blocks/forms/feature.py
cmsplugin_blocks/forms/hero.py
cmsplugin_blocks/forms/slider.py
cmsplugin_blocks/locale/django.pot
cmsplugin_blocks/locale/en/LC_MESSAGES/django.mo
cmsplugin_blocks/locale/en/LC_MESSAGES/django.po
cmsplugin_blocks/locale/fr/LC_MESSAGES/django.mo
cmsplugin_blocks/locale/fr/LC_MESSAGES/django.po
cmsplugin_blocks/migrations/0001_initial.py
cmsplugin_blocks/migrations/0002_add_slide_item_order.py
cmsplugin_blocks/migrations/0003_slideitem_title.py
cmsplugin_blocks/migrations/0004_change_image_as_filefield_.py
cmsplugin_blocks/migrations/0005_v1-0-0_changes.py
cmsplugin_blocks/migrations/0006_alter_card_content.py
cmsplugin_blocks/migrations/0007_add_image_alt.py
